{
  "type": "Collection",
  "id": "meteorological_variables",
  "stac_version": "1.1.0",
  "description": "These indicators show global variations for meteorological variables on a monthly basis from 1959 to 2023",
  "links": [
    {
      "rel": "root",
      "href": "../catalog.json",
      "type": "application/json",
      "title": "RACE"
    },
    {
      "rel": "child",
      "href": "./temperature/collection.json",
      "type": "application/json",
      "title": "Global temperature",
      "endpointtype": "Sentinel Hub_byoc",
      "subtitle": "Global temperature description",
      "code": "CDS1_temperature",
      "id": "temperature",
      "themes": [
        "air"
      ],
      "tags": [
        "Copernicus Services",
        "C3S",
        "CDS",
        "Multi-sensors",
        "Open data"
      ],
      "agency": [
        "European Commission",
        "ECMWF"
      ],
      "subcode": "CDS1_temperature",
      "otherSources": [
        "ERA5"
      ]
    },
    {
      "rel": "child",
      "href": "./relative_humidity/collection.json",
      "type": "application/json",
      "title": "Relative humidity",
      "endpointtype": "Sentinel Hub_byoc",
      "subtitle": "Global relative humidity",
      "code": "CDS2_relative_humidity",
      "id": "relative_humidity",
      "themes": [
        "air"
      ],
      "tags": [
        "Copernicus Services",
        "C3S",
        "CDS",
        "Multi-sensors",
        "Open data"
      ],
      "agency": [
        "European Commission",
        "ECMWF"
      ],
      "subcode": "CDS2_relative_humidity",
      "otherSources": [
        "ERA5"
      ]
    },
    {
      "rel": "child",
      "href": "./wind_10m_u/collection.json",
      "type": "application/json",
      "title": "Wind U Field",
      "endpointtype": "Sentinel Hub_byoc",
      "subtitle": "Gridded ERA5 is the fifth generation ECMWF reanalysis for the global climate and weather for the past 4 to 7 decades. This parameter is the wind U field",
      "code": "CDS3",
      "id": "wind_10m_u",
      "themes": [
        "air"
      ],
      "tags": [
        "Copernicus Services",
        "C3S",
        "CDS",
        "Multi-sensors",
        "Open data"
      ],
      "agency": [
        "European Commission",
        "ECMWF"
      ],
      "subcode": "CDS3",
      "otherSources": [
        "ERA5"
      ]
    },
    {
      "rel": "child",
      "href": "./wind_10m_v/collection.json",
      "type": "application/json",
      "title": "Wind V Field",
      "endpointtype": "Sentinel Hub_byoc",
      "subtitle": "Gridded ERA5 is the fifth generation ECMWF reanalysis for the global climate and weather for the past 4 to 7 decades. This parameter is the wind V field",
      "code": "CDS4",
      "id": "wind_10m_v",
      "themes": [
        "air"
      ],
      "tags": [
        "Copernicus Services",
        "C3S",
        "CDS",
        "Multi-sensors",
        "Open data"
      ],
      "agency": [
        "European Commission",
        "ECMWF"
      ],
      "subcode": "CDS4",
      "otherSources": [
        "ERA5"
      ]
    },
    {
      "rel": "parent",
      "href": "../catalog.json",
      "type": "application/json",
      "title": "RACE"
    }
  ],
  "subcode": "C3S",
  "title": "C3S meteorological variables",
  "extent": {
    "spatial": {
      "bbox": [
        [
          -180.0,
          -90.22495138408348,
          180.0,
          90.125
        ],
        [
          -180.0,
          -90.22495138408348,
          180.0,
          90.125
        ],
        [
          -180.0,
          -90.22495138408348,
          180.0,
          90.125
        ],
        [
          -180.0,
          -90.22495138408348,
          180.0,
          90.125
        ],
        [
          -180.0,
          -90.22495138408348,
          180.0,
          90.125
        ]
      ]
    },
    "temporal": {
      "interval": [
        [
          "1959-01-01T00:00:00Z",
          "2024-03-01T00:00:00Z"
        ]
      ]
    }
  },
  "license": "other",
  "summaries": {
    "subcode": [
      "CDS1_temperature",
      "CDS3",
      "CDS4",
      "CDS2_relative_humidity"
    ],
    "themes": [
      "air"
    ],
    "thumbnail": [
      "https://raw.githubusercontent.com/eurodatacube/eodash-assets/main/collections/CDS1_temperature/CDS1_temperature.png",
      "https://raw.githubusercontent.com/eurodatacube/eodash-assets/main/collections/CDS2_relative_humidity/CDS2_relative_humidity.png",
      "https://raw.githubusercontent.com/eurodatacube/eodash-assets/main/collections/CDS4_wind_10m_v/CDS4_wind_10m_v.png",
      "https://raw.githubusercontent.com/eurodatacube/eodash-assets/main/collections/CDS3_wind_10m_u/CDS3_wind_10m_u.png"
    ]
  }
}